mrlpy/__init__.py
mrlpy/exceptions.py
mrlpy/mcommand.py
mrlpy/mcompat-run.py
mrlpy/mcompat.py
mrlpy/mevent.py
mrlpy/meventdispatch.py
mrlpy/proxy.py
mrlpy/proxygen.py
mrlpy/testService.py
mrlpy/utils.py
mrlpy/framework/deserializer.py
mrlpy/framework/interfaces.py
mrlpy/framework/mrl_dataclass.py
mrlpy/framework/runtime.py
mrlpy/framework/serializer.py
mrlpy/framework/service.py
mrlpy/service/__init__.py
mrlpy/service/data/__init__.py
mrlpy/service/data/chat.py
mrlpy-2.0.0.dist-info/METADATA
mrlpy-2.0.0.dist-info/WHEEL
mrlpy-2.0.0.dist-info/licenses/LICENSE
mrlpy-2.0.0.dist-info/RECORD
