Metadata-Version: 2.1
Name: mrlpy
Version: 2.0.0
Summary: Python API to MyRobotLab
Project-URL: Homepage, http://github.com/AutonomicPerfection/mrlpy
Author-email: AutonomicPerfectionist <bwtbutler@hotmail.com>
License-File: LICENSE
Requires-Dist: requests
Requires-Dist: websocket-client
